{
  "dashboard": {
    "id": null,
    "title": "SmartCloudOps AI - Advanced AI/ML Monitoring",
    "tags": ["smartcloudops", "ai", "ml", "monitoring"],
    "style": "dark",
    "timezone": "browser",
    "panels": [
      {
        "id": 1,
        "title": "AI Model Performance Overview",
        "type": "stat",
        "targets": [
          {
            "expr": "ai_model_accuracy",
            "legendFormat": "Model Accuracy"
          },
          {
            "expr": "ai_model_precision",
            "legendFormat": "Model Precision"
          },
          {
            "expr": "ai_model_recall",
            "legendFormat": "Model Recall"
          },
          {
            "expr": "ai_model_f1_score",
            "legendFormat": "F1 Score"
          }
        ],
        "fieldConfig": {
          "defaults": {
            "color": {
              "mode": "palette-classic"
            },
            "custom": {
              "displayMode": "list",
              "orientation": "horizontal"
            },
            "mappings": [],
            "thresholds": {
              "steps": [
                {
                  "color": "red",
                  "value": null
                },
                {
                  "color": "yellow",
                  "value": 0.7
                },
                {
                  "color": "green",
                  "value": 0.85
                }
              ]
            }
          }
        },
        "gridPos": {
          "h": 8,
          "w": 12,
          "x": 0,
          "y": 0
        }
      },
      {
        "id": 2,
        "title": "Model Drift Detection",
        "type": "timeseries",
        "targets": [
          {
            "expr": "ai_model_drift_score",
            "legendFormat": "Drift Score"
          },
          {
            "expr": "ai_data_drift_score",
            "legendFormat": "Data Drift"
          }
        ],
        "fieldConfig": {
          "defaults": {
            "color": {
              "mode": "palette-classic"
            },
            "custom": {
              "axisLabel": "",
              "axisPlacement": "auto",
              "barAlignment": 0,
              "drawStyle": "line",
              "fillOpacity": 10,
              "gradientMode": "none",
              "hideFrom": {
                "legend": false,
                "tooltip": false,
                "vis": false
              },
              "lineInterpolation": "linear",
              "lineWidth": 1,
              "pointSize": 5,
              "scaleDistribution": {
                "type": "linear"
              },
              "showPoints": "never",
              "spanNulls": false,
              "stacking": {
                "group": "A",
                "mode": "none"
              },
              "thresholdsStyle": {
                "mode": "off"
              }
            },
            "mappings": [],
            "thresholds": {
              "mode": "absolute",
              "steps": [
                {
                  "color": "green",
                  "value": null
                },
                {
                  "color": "yellow",
                  "value": 0.3
                },
                {
                  "color": "red",
                  "value": 0.5
                }
              ]
            },
            "unit": "short"
          }
        },
        "gridPos": {
          "h": 8,
          "w": 12,
          "x": 12,
          "y": 0
        }
      },
      {
        "id": 3,
        "title": "Continuous Learning Statistics",
        "type": "stat",
        "targets": [
          {
            "expr": "ai_learning_cycles_total",
            "legendFormat": "Learning Cycles"
          },
          {
            "expr": "ai_models_trained_total",
            "legendFormat": "Models Trained"
          },
          {
            "expr": "ai_retraining_events_total",
            "legendFormat": "Retraining Events"
          },
          {
            "expr": "ai_active_learning_requests",
            "legendFormat": "Active Learning Requests"
          }
        ],
        "fieldConfig": {
          "defaults": {
            "color": {
              "mode": "palette-classic"
            },
            "custom": {
              "displayMode": "list",
              "orientation": "horizontal"
            },
            "mappings": [],
            "thresholds": {
              "steps": [
                {
                  "color": "green",
                  "value": null
                }
              ]
            }
          }
        },
        "gridPos": {
          "h": 8,
          "w": 12,
          "x": 0,
          "y": 8
        }
      },
      {
        "id": 4,
        "title": "Autonomous Operations Performance",
        "type": "stat",
        "targets": [
          {
            "expr": "ai_autonomous_actions_total",
            "legendFormat": "Total Actions"
          },
          {
            "expr": "ai_autonomous_success_rate",
            "legendFormat": "Success Rate"
          },
          {
            "expr": "ai_manual_interventions",
            "legendFormat": "Manual Interventions"
          },
          {
            "expr": "ai_automation_confidence",
            "legendFormat": "Confidence Score"
          }
        ],
        "fieldConfig": {
          "defaults": {
            "color": {
              "mode": "palette-classic"
            },
            "custom": {
              "displayMode": "list",
              "orientation": "horizontal"
            },
            "mappings": [],
            "thresholds": {
              "steps": [
                {
                  "color": "red",
                  "value": null
                },
                {
                  "color": "yellow",
                  "value": 0.7
                },
                {
                  "color": "green",
                  "value": 0.9
                }
              ]
            },
            "unit": "percent"
          }
        },
        "gridPos": {
          "h": 8,
          "w": 12,
          "x": 12,
          "y": 8
        }
      },
      {
        "id": 5,
        "title": "Knowledge Base Growth",
        "type": "timeseries",
        "targets": [
          {
            "expr": "ai_knowledge_nodes_total",
            "legendFormat": "Knowledge Nodes"
          },
          {
            "expr": "ai_knowledge_edges_total",
            "legendFormat": "Knowledge Edges"
          },
          {
            "expr": "ai_experiences_added_total",
            "legendFormat": "Experiences Added"
          }
        ],
        "fieldConfig": {
          "defaults": {
            "color": {
              "mode": "palette-classic"
            },
            "custom": {
              "axisLabel": "",
              "axisPlacement": "auto",
              "barAlignment": 0,
              "drawStyle": "line",
              "fillOpacity": 10,
              "gradientMode": "none",
              "hideFrom": {
                "legend": false,
                "tooltip": false,
                "vis": false
              },
              "lineInterpolation": "linear",
              "lineWidth": 1,
              "pointSize": 5,
              "scaleDistribution": {
                "type": "linear"
              },
              "showPoints": "never",
              "spanNulls": false,
              "stacking": {
                "group": "A",
                "mode": "none"
              },
              "thresholdsStyle": {
                "mode": "off"
              }
            },
            "mappings": [],
            "thresholds": {
              "mode": "absolute",
              "steps": [
                {
                  "color": "green",
                  "value": null
                }
              ]
            },
            "unit": "short"
          }
        },
        "gridPos": {
          "h": 8,
          "w": 12,
          "x": 0,
          "y": 16
        }
      },
      {
        "id": 6,
        "title": "Reinforcement Learning Performance",
        "type": "timeseries",
        "targets": [
          {
            "expr": "ai_rl_q_value_avg",
            "legendFormat": "Average Q-Value"
          },
          {
            "expr": "ai_rl_reward_avg",
            "legendFormat": "Average Reward"
          },
          {
            "expr": "ai_rl_exploration_rate",
            "legendFormat": "Exploration Rate"
          }
        ],
        "fieldConfig": {
          "defaults": {
            "color": {
              "mode": "palette-classic"
            },
            "custom": {
              "axisLabel": "",
              "axisPlacement": "auto",
              "barAlignment": 0,
              "drawStyle": "line",
              "fillOpacity": 10,
              "gradientMode": "none",
              "hideFrom": {
                "legend": false,
                "tooltip": false,
                "vis": false
              },
              "lineInterpolation": "linear",
              "lineWidth": 1,
              "pointSize": 5,
              "scaleDistribution": {
                "type": "linear"
              },
              "showPoints": "never",
              "spanNulls": false,
              "stacking": {
                "group": "A",
                "mode": "none"
              },
              "thresholdsStyle": {
                "mode": "off"
              }
            },
            "mappings": [],
            "thresholds": {
              "mode": "absolute",
              "steps": [
                {
                  "color": "green",
                  "value": null
                }
              ]
            },
            "unit": "short"
          }
        },
        "gridPos": {
          "h": 8,
          "w": 12,
          "x": 12,
          "y": 16
        }
      },
      {
        "id": 7,
        "title": "A/B Testing Experiments",
        "type": "table",
        "targets": [
          {
            "expr": "ai_ab_testing_experiments",
            "format": "table",
            "instant": true
          }
        ],
        "fieldConfig": {
          "defaults": {
            "color": {
              "mode": "palette-classic"
            },
            "custom": {
              "align": "auto",
              "displayMode": "auto"
            },
            "mappings": [],
            "thresholds": {
              "mode": "absolute",
              "steps": [
                {
                  "color": "green",
                  "value": null
                }
              ]
            }
          }
        },
        "gridPos": {
          "h": 8,
          "w": 12,
          "x": 0,
          "y": 24
        }
      },
      {
        "id": 8,
        "title": "Model Registry Status",
        "type": "table",
        "targets": [
          {
            "expr": "ai_model_registry_status",
            "format": "table",
            "instant": true
          }
        ],
        "fieldConfig": {
          "defaults": {
            "color": {
              "mode": "palette-classic"
            },
            "custom": {
              "align": "auto",
              "displayMode": "auto"
            },
            "mappings": [],
            "thresholds": {
              "mode": "absolute",
              "steps": [
                {
                  "color": "green",
                  "value": null
                }
              ]
            }
          }
        },
        "gridPos": {
          "h": 8,
          "w": 12,
          "x": 12,
          "y": 24
        }
      },
      {
        "id": 9,
        "title": "AI Recommendation Accuracy",
        "type": "gauge",
        "targets": [
          {
            "expr": "ai_recommendation_accuracy",
            "legendFormat": "Recommendation Accuracy"
          }
        ],
        "fieldConfig": {
          "defaults": {
            "color": {
              "mode": "palette-classic"
            },
            "custom": {
              "displayMode": "gauge",
              "orientation": "auto",
              "reduceOptions": {
                "calcs": [
                  "lastNotNull"
                ],
                "fields": "",
                "values": false
              },
              "showThresholdLabels": false,
              "showThresholdMarkers": true
            },
            "mappings": [],
            "thresholds": {
              "steps": [
                {
                  "color": "red",
                  "value": null
                },
                {
                  "color": "yellow",
                  "value": 0.7
                },
                {
                  "color": "green",
                  "value": 0.9
                }
              ]
            },
            "unit": "percent"
          }
        },
        "gridPos": {
          "h": 8,
          "w": 8,
          "x": 0,
          "y": 32
        }
      },
      {
        "id": 10,
        "title": "Active Learning Requests",
        "type": "timeseries",
        "targets": [
          {
            "expr": "ai_active_learning_requests_total",
            "legendFormat": "Total Requests"
          },
          {
            "expr": "ai_active_learning_responses_total",
            "legendFormat": "Responses Received"
          },
          {
            "expr": "ai_active_learning_accuracy_improvement",
            "legendFormat": "Accuracy Improvement"
          }
        ],
        "fieldConfig": {
          "defaults": {
            "color": {
              "mode": "palette-classic"
            },
            "custom": {
              "axisLabel": "",
              "axisPlacement": "auto",
              "barAlignment": 0,
              "drawStyle": "line",
              "fillOpacity": 10,
              "gradientMode": "none",
              "hideFrom": {
                "legend": false,
                "tooltip": false,
                "vis": false
              },
              "lineInterpolation": "linear",
              "lineWidth": 1,
              "pointSize": 5,
              "scaleDistribution": {
                "type": "linear"
              },
              "showPoints": "never",
              "spanNulls": false,
              "stacking": {
                "group": "A",
                "mode": "none"
              },
              "thresholdsStyle": {
                "mode": "off"
              }
            },
            "mappings": [],
            "thresholds": {
              "mode": "absolute",
              "steps": [
                {
                  "color": "green",
                  "value": null
                }
              ]
            },
            "unit": "short"
          }
        },
        "gridPos": {
          "h": 8,
          "w": 16,
          "x": 8,
          "y": 32
        }
      }
    ],
    "time": {
      "from": "now-24h",
      "to": "now"
    },
    "timepicker": {},
    "templating": {
      "list": []
    },
    "annotations": {
      "list": []
    },
    "refresh": "30s",
    "schemaVersion": 27,
    "version": 1,
    "links": []
  }
}
